shitcoin/__init__.py
shitcoin/cw20.py
shitcoin-4.2.0.dist-info/LICENSE
shitcoin-4.2.0.dist-info/METADATA
shitcoin-4.2.0.dist-info/WHEEL
shitcoin-4.2.0.dist-info/top_level.txt
shitcoin-4.2.0.dist-info/RECORD
