Metadata-Version: 2.1
Name: shitcoin
Version: 4.2.0
Summary: Changing the world, one DAO at a time.
Home-page: https://github.com/bmorphism/shitcoin
Author: Bartolomeə
Author-email: barton@bmorphism.xyz
License: The Unlicense
Project-URL: Bug Tracker, https://github.com/bmorphism/shitcoin/issues
Keywords: shitcoin,degen,blockchain,dao,cw20,ibc,defi,denom,permissionless,token,anarchy
Platform: UNKNOWN
Classifier: Programming Language :: Python :: 3
Classifier: License :: OSI Approved :: The Unlicense (Unlicense)
Classifier: Intended Audience :: Developers
Classifier: Intended Audience :: Financial and Insurance Industry
Classifier: Intended Audience :: Legal Industry
Classifier: Intended Audience :: Science/Research
Classifier: Intended Audience :: Religion
Classifier: Intended Audience :: Other Audience
Classifier: Topic :: Internet
Classifier: Topic :: Games/Entertainment :: Simulation
Classifier: Development Status :: 3 - Alpha
Requires-Python: >=3.6
License-File: LICENSE
